ai_terminal/__init__.py
ai_terminal/config_manager.py
ai_terminal/core.py
ai_terminal/history_manager.py
ai_terminal/http_utils.py
ai_terminal/llm_client.py
ai_terminal/main.py
ai_terminal/plan_executor.py
ai_terminal/safety.py
magic_terminal_cli-1.0.0.dist-info/licenses/LICENSE
magic_terminal_cli-1.0.0.dist-info/METADATA
magic_terminal_cli-1.0.0.dist-info/WHEEL
magic_terminal_cli-1.0.0.dist-info/entry_points.txt
magic_terminal_cli-1.0.0.dist-info/top_level.txt
magic_terminal_cli-1.0.0.dist-info/RECORD
