Metadata-Version: 2.4
Name: magic-terminal-cli
Version: 1.0.0
Summary: A magical terminal assistant that understands natural language and makes command-line operations effortless
Home-page: https://github.com/Yogesh-developer/magic-terminal
Author: Magic Terminal Team
Author-email: support@magicterminal.dev
Project-URL: Bug Reports, https://github.com/Yogesh-developer/magic-terminal/issues
Project-URL: Source, https://github.com/Yogesh-developer/magic-terminal
Project-URL: Documentation, https://github.com/Yogesh-developer/magic-terminal/wiki
Keywords: terminal,magic,assistant,automation,cli,shell,natural-language
Classifier: Development Status :: 4 - Beta
Classifier: Intended Audience :: Developers
Classifier: Intended Audience :: System Administrators
Classifier: License :: OSI Approved :: MIT License
Classifier: Operating System :: OS Independent
Classifier: Programming Language :: Python :: 3
Classifier: Programming Language :: Python :: 3.8
Classifier: Programming Language :: Python :: 3.9
Classifier: Programming Language :: Python :: 3.10
Classifier: Programming Language :: Python :: 3.11
Classifier: Topic :: System :: Shells
Classifier: Topic :: System :: System Shells
Classifier: Topic :: Utilities
Requires-Python: >=3.8
License-File: LICENSE
Requires-Dist: requests>=2.28.0
Requires-Dist: psutil>=5.9.0
Requires-Dist: jsonschema>=4.0.0
Provides-Extra: dev
Requires-Dist: pytest>=7.0.0; extra == "dev"
Requires-Dist: black>=22.0.0; extra == "dev"
Provides-Extra: full
Requires-Dist: colorama>=0.4.4; extra == "full"
Requires-Dist: rich>=12.0.0; extra == "full"
Requires-Dist: prompt-toolkit>=3.0.0; extra == "full"
Dynamic: author
Dynamic: author-email
Dynamic: classifier
Dynamic: description
Dynamic: description-content-type
Dynamic: home-page
Dynamic: keywords
Dynamic: license-file
Dynamic: project-url
Dynamic: provides-extra
Dynamic: requires-dist
Dynamic: requires-python
Dynamic: summary
